cse4010_spring25/verilog/lab3b/fullSubtractor.v
/*
 * File: fullSubtractor.v
 * Description: Implements a 1-bit full subtractor using half subtractors
 * A full subtractor subtracts three bits (A, B, and borrow-in) and produces difference and borrow-out
 * A full subtractor is built from two half subtractors and an OR gate; 
 * The first half subtractor subtracts B from A and produces a difference and a borrow
 * The second half subtractor subtracts the borrow-in from the difference of the first half subtractor
 * The OR gate combines the borrows from the two half subtractors to produce the final borrow-out
 */

// Half Subtractor Module - Subtracts one bit from another and produces difference and borrow
module halfSubtractor(op1, op2, diff, borrow);

    // Inputs - two 1-bit operands
    input op1, op2;
    // Outputs - difference and borrow bits
    output diff, borrow;

    // XOR operation - difference is 1 if op1 and op2 are different
    assign diff = op1 ^ op2;

    // AND operation with NOT on op2 - borrow is 1 if op1=1 and op2=0
    assign borrow = op1 & !op2;

endmodule

// Full Subtractor Module - Subtracts three bits (A, B, borrow-in) and produces difference and borrow-out
module fullSubtractor(A, B, Bin, diff, Bout);

    // Input ports
    input A, B, Bin;  // A is minuend, B is subtrahend, Bin is borrow-in from previous subtraction
    // Output ports
    output diff, Bout; // diff is the difference bit, Bout propagates borrow to next subtraction
    
    // Internal connections - wires to connect the half subtractors
    wire c;  // Difference output from first half subtractor
    wire d;  // Borrow output from first half subtractor
    wire e;  // Difference output from second half subtractor (unused)
    wire f;  // Borrow output from second half subtractor

    // First half subtractor - subtracts B from A
    halfSubtractor u1(A, B, c, d);

    // Second half subtractor - subtracts Bin from the result of first half subtractor
    halfSubtractor u2(c, Bin, diff, f);

    // Final borrow out is OR of both half subtractor borrows
    assign Bout = f | d;  // | is the OR operator

endmodule

cse4010_spring25/verilog/lab3b/fullSubtractor_tb.v
/*
 * File: fullSubtractor_tb.v
 * Description: Testbench for the 1-bit full subtractor
 * Tests all possible input combinations (0-7) for A, B, Bin
 * The testbench uses a loop to iterate through all possible input combinations
 * It displays the results of each test case
 */
 
// Define timescale for simulation: 1 nanosecond time unit, 1 nanosecond precision
`timescale 1 ns / 1 ns
// Include the module to be tested
`include "fullSubtractor.v"

// Testbench module - no external ports
module fullSubtractor_tb;

// Test inputs - declared as registers since they will be driven
reg A, B, Bin;
// Test outputs - declared as wires since they will be monitored
wire diff, Bout;

// Instantiate the Unit Under Test (UUT) - connect to test signals
fullSubtractor uut(A, B, Bin, diff, Bout);

// Test sequence
initial begin
    // Generate VCD file for waveform viewing
    $dumpfile("fullSubtractor_tb.vcd");
    // Dump variables from the testbench (0 means all variables)
    $dumpvars(0, fullSubtractor_tb);
    
    // Test case 0: A=0, B=0, Bin=0
    {A, B, Bin} = 3'd0; #20;
    // Test case 1: A=0, B=0, Bin=1
    {A, B, Bin} = 3'd1; #20;
    // Test case 2: A=0, B=1, Bin=0
    {A, B, Bin} = 3'd2; #20;
    // Test case 3: A=0, B=1, Bin=1
    {A, B, Bin} = 3'd3; #20;
    // Test case 4: A=1, B=0, Bin=0
    {A, B, Bin} = 3'd4; #20;
    // Test case 5: A=1, B=0, Bin=1
    {A, B, Bin} = 3'd5; #20;
    // Test case 6: A=1, B=1, Bin=0
    {A, B, Bin} = 3'd6; #20;
    // Test case 7: A=1, B=1, Bin=1
    {A, B, Bin} = 3'd7; #20;
    // Display a message to indicate completion of test cases
    $display("Finished subtractions!");
    
end

endmodule

cse4010_spring25/verilog/lab3b/fullSubtractor_tb.vcd
$date
	Sat Mar  1 21:37:51 2025
$end
$version
	Icarus Verilog
$end
$timescale
	1ns
$end
$scope module fullSubtractor_tb $end
$var wire 1 ! diff $end
$var wire 1 " Bout $end
$var reg 1 # A $end
$var reg 1 $ B $end
$var reg 1 % Bin $end
$scope module uut $end
$var wire 1 # A $end
$var wire 1 $ B $end
$var wire 1 % Bin $end
$var wire 1 " Bout $end
$var wire 1 & f $end
$var wire 1 ! diff $end
$var wire 1 ' d $end
$var wire 1 ( c $end
$scope module u1 $end
$var wire 1 ' borrow $end
$var wire 1 ( diff $end
$var wire 1 # op1 $end
$var wire 1 $ op2 $end
$upscope $end
$scope module u2 $end
$var wire 1 & borrow $end
$var wire 1 ! diff $end
$var wire 1 ( op1 $end
$var wire 1 % op2 $end
$upscope $end
$upscope $end
$upscope $end
$enddefinitions $end
$comment Show the parameter values. $end
$dumpall
$end
#0
$dumpvars
0(
0'
0&
0%
0$
0#
0"
0!
$end
#20
1!
1%
#40
1"
1&
1(
1!
1$
0%
#60
0"
0!
0&
1%
#80
1"
1'
1!
1&
1#
0$
0%
#100
0!
0&
1%
#120
0"
0(
0'
0!
0&
1$
0%
#140
1!
1%
